MANIFEST.in
README.md
setup.py
drf_permissions_router/__init__.py
drf_permissions_router/routers.py
drf_permissions_router.egg-info/PKG-INFO
drf_permissions_router.egg-info/SOURCES.txt
drf_permissions_router.egg-info/dependency_links.txt
drf_permissions_router.egg-info/requires.txt
drf_permissions_router.egg-info/top_level.txt
drf_permissions_router/runtests/__init__.py
drf_permissions_router/runtests/runtests.py
drf_permissions_router/runtests/settings.py